model_lib/__init__.py
model_lib/base_settings.py
model_lib/constants.py
model_lib/dump.py
model_lib/dump_functions.py
model_lib/errors.py
model_lib/fields.py
model_lib/model_base.py
model_lib/model_dump.py
model_lib/parse.py
model_lib/py.typed
model_lib/pydantic_utils.py
model_lib/static_settings.py
model_lib/yaml.py
model_lib/metadata/__init__.py
model_lib/metadata/context_dict.py
model_lib/metadata/metadata.py
model_lib/metadata/metadata_dump.py
model_lib/metadata/metadata_fields.py
model_lib/serialize/__init__.py
model_lib/serialize/base_64.py
model_lib/serialize/dump.py
model_lib/serialize/json_serialize.py
model_lib/serialize/parse.py
model_lib/serialize/toml_serialize.py
model_lib/serialize/yaml_serialize.py
model_lib-0.102.0.dist-info/METADATA
model_lib-0.102.0.dist-info/WHEEL
model_lib-0.102.0.dist-info/licenses/LICENSE
model_lib-0.102.0.dist-info/RECORD
