Metadata-Version: 2.4
Name: model-lib
Version: 0.102.0
Summary: Pydantic model utilities for serialization and settings
Author-email: EspenAlbert <espen.albert1@gmail.com>
License-Expression: MIT
License-File: LICENSE
Classifier: Development Status :: 4 - Beta
Classifier: Programming Language :: Python :: 3.13
Classifier: Programming Language :: Python :: 3.14
Requires-Python: >=3.13
Requires-Dist: platformdirs>=4.0
Requires-Dist: pydantic-settings>=2.8
Requires-Dist: pydantic>=2.11
Requires-Dist: pyyaml>=6.0.2
Requires-Dist: zero-3rdparty
Provides-Extra: toml
Requires-Dist: tomli-w~=1.1.0; extra == 'toml'
